{
  "de": "Đề 1",
  "monHoc": "Toán",
  "lop": 7,
  "kyThi": "Cuối học kỳ II",
  "thoiGian": 90,
  "tongDiem": 10.0,
  "thangMucDo": {
    "1": "NB - Nhận biết",
    "2": "TH - Thông hiểu",
    "3": "VD - Vận dụng",
    "4": "VDC - Vận dụng cao"
  },
  "soCau": 25,
  "cauHoi": [
    {
      "id": "D1-C1",
      "deNguon": "Đề 1",
      "loaiCau": "TN4",
      "mucDo": "NB",
      "mucDoSo": 1,
      "mucDoTen": "Nhận biết",
      "diem": 0.25,
      "chuDe": "Tỉ lệ thức",
      "nodeGraph": "l7-ti-le-thuc",
      "deBai": "Nếu $\\dfrac{x}{3}=\\dfrac{4}{9}$ thì ta có:",
      "hinhAnh": null,
      "phuongAn": {
        "A": "$x=\\dfrac{4}{9}$",
        "B": "$x=-\\dfrac{4}{9}$",
        "C": "$x=\\dfrac{4}{3}$",
        "D": "$x=-\\dfrac{4}{3}$"
      },
      "dapAn": "C",
      "loiGiai": "Từ tỉ lệ thức, nhân chéo: $9x = 3\\cdot 4 = 12 \\Rightarrow x=\\dfrac{12}{9}=\\dfrac{4}{3}$.",
      "phanTichSai": {
        "A": "Lấy thẳng tử số 4 và mẫu 9 mà không nhân chéo.",
        "B": "Thêm dấu âm không có căn cứ.",
        "D": "Đúng độ lớn $\\frac{4}{3}$ nhưng gán nhầm dấu âm."
      },
      "goiYSocratic": [
        "Hai phân số bằng nhau thì tích chéo thế nào?",
        "$9\\cdot x$ bằng bao nhiêu?",
        "Rút gọn $\\frac{12}{9}$."
      ]
    },
    {
      "id": "D1-C2",
      "deNguon": "Đề 1",
      "loaiCau": "TN4",
      "mucDo": "NB",
      "mucDoSo": 1,
      "mucDoTen": "Nhận biết",
      "diem": 0.25,
      "chuDe": "Tỉ lệ thức",
      "nodeGraph": "l7-ti-le-thuc",
      "deBai": "Trong các cặp tỉ số sau, cặp tỉ số nào lập thành một tỉ lệ thức?",
      "hinhAnh": null,
      "phuongAn": {
        "A": "$\\dfrac{8}{12}$ và $\\dfrac{12}{10}$",
        "B": "$\\dfrac{3}{5}$ và $\\dfrac{6}{10}$",
        "C": "$\\dfrac{0,25}{1,75}$ và $\\dfrac{5}{30}$",
        "D": "$\\dfrac{1}{1,5}$ và $\\dfrac{2}{5}$"
      },
      "dapAn": "B",
      "loiGiai": "Hai tỉ số lập tỉ lệ thức khi bằng nhau: $\\dfrac{3}{5}=\\dfrac{6}{10}$ (vì $3\\cdot10=5\\cdot6=30$).",
      "phanTichSai": {
        "A": "$8\\cdot10=80\\neq12\\cdot12=144$.",
        "C": "$0,25\\cdot30=7,5\\neq1,75\\cdot5=8,75$.",
        "D": "$1\\cdot5=5\\neq1,5\\cdot2=3$."
      },
      "goiYSocratic": [
        "Kiểm tra tích chéo của từng cặp.",
        "Cặp nào cho tích chéo bằng nhau?"
      ]
    },
    {
      "id": "D1-C3",
      "deNguon": "Đề 1",
      "loaiCau": "TN4",
      "mucDo": "NB",
      "mucDoSo": 1,
      "mucDoTen": "Nhận biết",
      "diem": 0.25,
      "chuDe": "Biểu thức đại số",
      "nodeGraph": "l7-bieu-thuc-dai-so",
      "deBai": "Biểu thức đại số nào biểu thị chu vi hình chữ nhật có chiều dài $7\\,(cm)$ và chiều rộng $x\\,(cm)$?",
      "hinhAnh": null,
      "phuongAn": {
        "A": "$(7+x)\\cdot 2$",
        "B": "$(7+x):2$",
        "C": "$(7x)\\cdot 2$",
        "D": "$7x$"
      },
      "dapAn": "A",
      "loiGiai": "Chu vi hình chữ nhật $=$ (dài $+$ rộng)$\\times 2 = (7+x)\\cdot 2$.",
      "phanTichSai": {
        "B": "Đây là nửa tổng, không phải chu vi.",
        "C": "Nhân dài với rộng rồi nhân 2 — nhầm sang diện tích.",
        "D": "$7x$ là diện tích, không phải chu vi."
      },
      "goiYSocratic": [
        "Công thức chu vi hình chữ nhật là gì?",
        "'Dài cộng rộng' viết thế nào với $x$?"
      ]
    },
    {
      "id": "D1-C4",
      "deNguon": "Đề 1",
      "loaiCau": "TN4",
      "mucDo": "NB",
      "mucDoSo": 1,
      "mucDoTen": "Nhận biết",
      "diem": 0.25,
      "chuDe": "Đa thức một biến",
      "nodeGraph": "l7-da-thuc-mot-bien",
      "deBai": "Đa thức nào sau đây là đa thức một biến?",
      "hinhAnh": null,
      "phuongAn": {
        "A": "$2x^2+y-5$",
        "B": "$3x^3+2x^2+x-1$",
        "C": "$x+y+z$",
        "D": "$x^2y+y-3$"
      },
      "dapAn": "B",
      "loiGiai": "Đa thức một biến chỉ chứa một chữ (biến). Chỉ $3x^3+2x^2+x-1$ dùng duy nhất biến $x$.",
      "phanTichSai": {
        "A": "Có cả $x$ và $y$ → hai biến.",
        "C": "Có ba biến $x,y,z$.",
        "D": "Có cả $x$ và $y$."
      },
      "goiYSocratic": [
        "Đa thức một biến nghĩa là có mấy chữ?",
        "Đếm số loại chữ trong mỗi đáp án."
      ]
    },
    {
      "id": "D1-C5",
      "deNguon": "Đề 1",
      "loaiCau": "TN4",
      "mucDo": "NB",
      "mucDoSo": 1,
      "mucDoTen": "Nhận biết",
      "diem": 0.25,
      "chuDe": "Đa thức một biến",
      "nodeGraph": "l7-da-thuc-mot-bien",
      "deBai": "Cho đa thức $Q(x)=6x-6$. Nghiệm của đa thức $Q(x)$ là?",
      "hinhAnh": null,
      "phuongAn": {
        "A": "$x=1$",
        "B": "$x=2$",
        "C": "$x=-1$",
        "D": "$x=-2$"
      },
      "dapAn": "A",
      "loiGiai": "Nghiệm là giá trị làm $Q(x)=0$: $6x-6=0 \\Rightarrow x=1$.",
      "phanTichSai": {
        "B": "Thay $x=2$: $6\\cdot2-6=6\\neq0$.",
        "C": "Thay $x=-1$: $-12\\neq0$.",
        "D": "Thay $x=-2$: $-18\\neq0$."
      },
      "goiYSocratic": [
        "Nghiệm của đa thức là gì?",
        "Giải $6x-6=0$."
      ]
    },
    {
      "id": "D1-C6",
      "deNguon": "Đề 1",
      "loaiCau": "TN4",
      "mucDo": "NB",
      "mucDoSo": 1,
      "mucDoTen": "Nhận biết",
      "diem": 0.25,
      "chuDe": "Đa thức một biến",
      "nodeGraph": "l7-da-thuc-mot-bien",
      "deBai": "Cho $P(x)=x+3x^2-5+2x^3$. Cách biểu diễn nào sắp xếp theo lũy thừa **tăng** của biến?",
      "hinhAnh": null,
      "phuongAn": {
        "A": "$x+3x^2+2x^3-5$",
        "B": "$2x^3+3x^2+x-5$",
        "C": "$-5+x+3x^2+2x^3$",
        "D": "$-5+x+2x^3+3x^2$"
      },
      "dapAn": "C",
      "loiGiai": "Tăng dần theo số mũ: hạng tử tự do ($-5$, mũ 0) $\\to x \\to 3x^2 \\to 2x^3$.",
      "phanTichSai": {
        "A": "Bắt đầu bằng $x$, để hạng tử tự do $-5$ ở cuối → không tăng đều.",
        "B": "Đây là sắp xếp **giảm** dần.",
        "D": "Cuối bị đảo: $2x^3$ (mũ 3) đứng trước $3x^2$ (mũ 2)."
      },
      "goiYSocratic": [
        "'Tăng' nghĩa là số mũ đi từ nhỏ đến lớn.",
        "Số mũ của $-5$ là bao nhiêu?"
      ]
    },
    {
      "id": "D1-C7",
      "deNguon": "Đề 1",
      "loaiCau": "TN4",
      "mucDo": "TH",
      "mucDoSo": 2,
      "mucDoTen": "Thông hiểu",
      "diem": 0.25,
      "chuDe": "Đa thức một biến",
      "nodeGraph": "l7-da-thuc-mot-bien",
      "deBai": "Bậc của đa thức $P(x)=5x^4-7x^7+x^2-3x+7x^7$ là?",
      "hinhAnh": null,
      "phuongAn": {
        "A": "Bậc $1$",
        "B": "Bậc $4$",
        "C": "Bậc $7$",
        "D": "Bậc $2$"
      },
      "dapAn": "B",
      "loiGiai": "Phải **thu gọn trước**: $-7x^7+7x^7=0$. Còn $5x^4+x^2-3x$, số mũ cao nhất là 4 → bậc 4.",
      "phanTichSai": {
        "A": "Nhầm sang bậc thấp nhất.",
        "C": "Chưa thu gọn nên tưởng còn $x^7$.",
        "D": "Lấy nhầm số mũ của $x^2$."
      },
      "goiYSocratic": [
        "Trước khi tìm bậc cần làm gì với các hạng tử đồng dạng?",
        "$-7x^7+7x^7$ bằng bao nhiêu?"
      ]
    },
    {
      "id": "D1-C8",
      "deNguon": "Đề 1",
      "loaiCau": "TN4",
      "mucDo": "TH",
      "mucDoSo": 2,
      "mucDoTen": "Thông hiểu",
      "diem": 0.25,
      "chuDe": "Đa thức một biến",
      "nodeGraph": "l7-da-thuc-mot-bien",
      "deBai": "Giá trị của đa thức $A(x)=x^3-2x^2-3x+1$ tại $x=-1$ là:",
      "hinhAnh": null,
      "phuongAn": {
        "A": "$-1$",
        "B": "$-5$",
        "C": "$1$",
        "D": "$-3$"
      },
      "dapAn": "C",
      "loiGiai": "Thay $x=-1$: $(-1)^3-2(-1)^2-3(-1)+1=-1-2+3+1=1$.",
      "phanTichSai": {
        "A": "Sai dấu ở $-3x$ (quên $-3\\cdot(-1)=+3$).",
        "B": "Cộng trừ sai dấu toàn phần.",
        "D": "Tính nhầm $(-1)^2$."
      },
      "goiYSocratic": [
        "$(-1)^3$ và $(-1)^2$ bằng bao nhiêu?",
        "Chú ý dấu của $-3\\cdot(-1)$."
      ]
    },
    {
      "id": "D1-C9",
      "deNguon": "Đề 1",
      "loaiCau": "TN4",
      "mucDo": "VD",
      "mucDoSo": 3,
      "mucDoTen": "Vận dụng",
      "diem": 0.25,
      "chuDe": "Đa thức một biến",
      "nodeGraph": "l7-da-thuc-mot-bien",
      "deBai": "Cho $(x+3)(2x-1)=2x^2+5x-3$. Thương của phép chia đa thức $2x^2+5x-3$ cho đa thức $x+3$ là:",
      "hinhAnh": null,
      "phuongAn": {
        "A": "$x$",
        "B": "$2x$",
        "C": "$2x-1$",
        "D": "$x+3$"
      },
      "dapAn": "C",
      "loiGiai": "Vì $2x^2+5x-3=(x+3)(2x-1)$ nên chia cho $(x+3)$ được thương $2x-1$.",
      "phanTichSai": {
        "A": "Chỉ lấy hạng tử đầu của thương.",
        "B": "Bỏ mất phần $-1$ của thương.",
        "D": "Đây là số chia, không phải thương."
      },
      "goiYSocratic": [
        "Đẳng thức cho sẵn phân tích $2x^2+5x-3$ thành tích gì?",
        "Chia cho $(x+3)$ thì còn lại thừa số nào?"
      ]
    },
    {
      "id": "D1-C10",
      "deNguon": "Đề 1",
      "loaiCau": "TN4",
      "mucDo": "NB",
      "mucDoSo": 1,
      "mucDoTen": "Nhận biết",
      "diem": 0.25,
      "chuDe": "Xác suất",
      "nodeGraph": "l7-xac-suat",
      "deBai": "Ống cắm bút có 1 bút vàng, 1 bút đỏ, 1 bút đen. Lần lượt lấy ra 2 bút. Gọi $A$: ''Lấy được bút đỏ ở lần thứ nhất''. Tập hợp kết quả làm $A$ xảy ra là:",
      "hinhAnh": null,
      "phuongAn": {
        "A": "$X=\\{$đỏ–vàng, đỏ–đen$\\}$",
        "B": "$X=\\{$đỏ–xanh, đỏ–vàng$\\}$",
        "C": "$X=\\{$đỏ–hồng, đỏ–đen$\\}$",
        "D": "$X=\\{$đỏ–vàng, đỏ–đỏ xanh$\\}$"
      },
      "dapAn": "A",
      "loiGiai": "Lần 1 là đỏ, lần 2 là một trong hai bút còn lại (vàng hoặc đen) → $\\{$đỏ–vàng, đỏ–đen$\\}$.",
      "phanTichSai": {
        "B": "Không có bút xanh trong ống.",
        "C": "Không có bút hồng trong ống.",
        "D": "'đỏ–đỏ' vô lí vì chỉ có một bút đỏ."
      },
      "goiYSocratic": [
        "Trong ống có những màu nào?",
        "Nếu lần 1 đã là đỏ thì lần 2 còn màu gì?"
      ]
    },
    {
      "id": "D1-C11",
      "deNguon": "Đề 1",
      "loaiCau": "TN4",
      "mucDo": "NB",
      "mucDoSo": 1,
      "mucDoTen": "Nhận biết",
      "diem": 0.25,
      "chuDe": "Xác suất",
      "nodeGraph": "l7-xac-suat",
      "deBai": "Chọn ngẫu nhiên một số trong $S=\\{1;3;5;7;9\\}$. Biến cố nào là biến cố **chắc chắn**?",
      "hinhAnh": null,
      "phuongAn": {
        "A": "$A$: 'Số được chọn là số lẻ'",
        "B": "$B$: 'Số được chọn là số 1'",
        "C": "$C$: 'Số được chọn là số chẵn'",
        "D": "$D$: 'Số được chọn là số 3'"
      },
      "dapAn": "A",
      "loiGiai": "Mọi phần tử của $S$ đều là số lẻ nên biến cố 'số lẻ' luôn xảy ra → chắc chắn.",
      "phanTichSai": {
        "B": "Chỉ xảy ra khi bốc trúng 1 → ngẫu nhiên.",
        "C": "$S$ không có số chẵn → biến cố không thể.",
        "D": "Chỉ xảy ra khi bốc trúng 3 → ngẫu nhiên."
      },
      "goiYSocratic": [
        "Biến cố chắc chắn là biến cố luôn xảy ra.",
        "Mọi số trong $S$ có tính chất chung gì?"
      ]
    },
    {
      "id": "D1-C12",
      "deNguon": "Đề 1",
      "loaiCau": "TN4",
      "mucDo": "TH",
      "mucDoSo": 2,
      "mucDoTen": "Thông hiểu",
      "diem": 0.25,
      "chuDe": "Xác suất",
      "nodeGraph": "l7-xac-suat",
      "deBai": "Gieo ngẫu nhiên xúc xắc một lần. Biến cố 'Mặt xuất hiện là mặt ba chấm' có xác suất bằng:",
      "hinhAnh": null,
      "phuongAn": {
        "A": "$\\dfrac{1}{6}$",
        "B": "$\\dfrac{1}{3}$",
        "C": "$\\dfrac{1}{2}$",
        "D": "$\\dfrac{2}{3}$"
      },
      "dapAn": "A",
      "loiGiai": "Xúc xắc có 6 mặt đồng khả năng, chỉ 1 mặt ba chấm → xác suất $=\\dfrac{1}{6}$.",
      "phanTichSai": {
        "B": "Nhầm mẫu số thành 3 (do 'ba chấm').",
        "C": "Nhầm như tung đồng xu.",
        "D": "Không có căn cứ."
      },
      "goiYSocratic": [
        "Xúc xắc có mấy mặt?",
        "Có mấy mặt ba chấm?"
      ]
    },
    {
      "id": "D1-C13",
      "deNguon": "Đề 1",
      "loaiCau": "TN4",
      "mucDo": "TH",
      "mucDoSo": 2,
      "mucDoTen": "Thông hiểu",
      "diem": 0.25,
      "chuDe": "Xác suất",
      "nodeGraph": "l7-xac-suat",
      "deBai": "Lớp $7A$ có 35 học sinh gồm 16 nam và 17 nữ, chọn ngẫu nhiên một nam và một nữ làm lớp trưởng và lớp phó. Biến cố nào là **biến cố chắc chắn**?",
      "hinhAnh": null,
      "phuongAn": {
        "A": "'Bạn nam làm lớp trưởng và bạn nữ làm lớp phó'",
        "B": "'Bạn nam làm lớp phó và bạn nữ làm lớp trưởng'",
        "C": "'Bạn nam hoặc bạn nữ sẽ làm lớp trưởng'",
        "D": "'Không có bạn nam nào làm lớp trưởng'"
      },
      "dapAn": "C",
      "loiGiai": "Đã chọn một nam và một nữ cho hai chức, nên chức lớp trưởng chắc chắn thuộc về nam hoặc nữ → luôn đúng.",
      "phanTichSai": {
        "A": "Chỉ là một trong hai cách phân công → ngẫu nhiên.",
        "B": "Cũng chỉ là một khả năng → ngẫu nhiên.",
        "D": "Có thể nam làm lớp trưởng → không thể chắc chắn."
      },
      "goiYSocratic": [
        "Hai người được chọn giữ hai chức, vậy lớp trưởng là ai trong hai người đó?",
        "Phát biểu nào luôn đúng dù phân công thế nào?"
      ]
    },
    {
      "id": "D1-C14",
      "deNguon": "Đề 1",
      "loaiCau": "TN4",
      "mucDo": "NB",
      "mucDoSo": 1,
      "mucDoTen": "Nhận biết",
      "diem": 0.25,
      "chuDe": "Tam giác — bất đẳng thức tam giác",
      "nodeGraph": null,
      "deBai": "Bộ ba độ dài nào có thể là ba cạnh của một tam giác?",
      "hinhAnh": null,
      "phuongAn": {
        "A": "$2cm;\\,3cm;\\,5cm$",
        "B": "$3cm;\\,4cm;\\,8cm$",
        "C": "$2cm;\\,5cm;\\,8cm$",
        "D": "$3cm;\\,4cm;\\,6cm$"
      },
      "dapAn": "D",
      "loiGiai": "Bất đẳng thức tam giác: tổng hai cạnh nhỏ $>$ cạnh lớn. $3+4=7>6$ ✔.",
      "phanTichSai": {
        "A": "$2+3=5$ (bằng, không lớn hơn) → không tạo tam giác.",
        "B": "$3+4=7<8$.",
        "C": "$2+5=7<8$."
      },
      "goiYSocratic": [
        "Quy tắc ba cạnh tam giác nói gì?",
        "So sánh tổng hai cạnh bé với cạnh lớn nhất."
      ],
      "canhBao": "Câu hình học — node kiến thức chưa có trong graph.json (mạch Hình học đang bỏ qua)."
    },
    {
      "id": "D1-C15",
      "deNguon": "Đề 1",
      "loaiCau": "TN4",
      "mucDo": "NB",
      "mucDoSo": 1,
      "mucDoTen": "Nhận biết",
      "diem": 0.25,
      "chuDe": "Đường vuông góc và đường xiên",
      "nodeGraph": null,
      "deBai": "Đường vuông góc kẻ từ $M$ xuống đường thẳng $a$ là (xem hình):",
      "hinhAnh": "de1_c15.png",
      "phuongAn": {
        "A": "$MA$",
        "B": "$MH$",
        "C": "$MB$",
        "D": "$MC$"
      },
      "dapAn": "B",
      "loiGiai": "$MH\\perp a$ tại $H$ (chân đường vuông góc), các đoạn $MA, MB, MC$ là đường xiên.",
      "phanTichSai": {
        "A": "Đường xiên.",
        "C": "Đường xiên.",
        "D": "Đường xiên."
      },
      "goiYSocratic": [
        "Đoạn nào tạo góc vuông với $a$?"
      ],
      "canhBao": "Câu hình học — node kiến thức chưa có trong graph.json (mạch Hình học đang bỏ qua)."
    },
    {
      "id": "D1-C16",
      "deNguon": "Đề 1",
      "loaiCau": "TN4",
      "mucDo": "NB",
      "mucDoSo": 1,
      "mucDoTen": "Nhận biết",
      "diem": 0.25,
      "chuDe": "Tam giác bằng nhau",
      "nodeGraph": null,
      "deBai": "Cho $\\triangle MNP=\\triangle HEF$. Khi đó ta có:",
      "hinhAnh": null,
      "phuongAn": {
        "A": "Đỉnh $M$ và đỉnh $E$ là hai đỉnh tương ứng",
        "B": "$MN=HE$",
        "C": "$MN=EF$",
        "D": "$\\hat{H}=\\hat{E}$"
      },
      "dapAn": "B",
      "loiGiai": "Theo thứ tự đỉnh $M\\!\\leftrightarrow\\!H,\\,N\\!\\leftrightarrow\\!E,\\,P\\!\\leftrightarrow\\!F$ nên cạnh $MN=HE$.",
      "phanTichSai": {
        "A": "$M$ tương ứng với $H$, không phải $E$.",
        "C": "$MN$ tương ứng $HE$, không phải $EF$.",
        "D": "$\\hat{H}$ tương ứng $\\hat{M}$, không phải $\\hat{E}$."
      },
      "goiYSocratic": [
        "Viết cặp đỉnh tương ứng theo đúng thứ tự.",
        "Cạnh $MN$ ứng với cạnh nào?"
      ],
      "canhBao": "Câu hình học — node kiến thức chưa có trong graph.json (mạch Hình học đang bỏ qua)."
    },
    {
      "id": "D1-C17",
      "deNguon": "Đề 1",
      "loaiCau": "TN4",
      "mucDo": "NB",
      "mucDoSo": 1,
      "mucDoTen": "Nhận biết",
      "diem": 0.25,
      "chuDe": "Hình lăng trụ đứng",
      "nodeGraph": null,
      "deBai": "Trong các hình sau, hình nào là hình lăng trụ đứng tứ giác? (xem hình)",
      "hinhAnh": "de1_c17.png",
      "phuongAn": {
        "A": "Hình 3",
        "B": "Hình 2",
        "C": "Hình 1",
        "D": "Hình 4"
      },
      "dapAn": "D",
      "loiGiai": "Lăng trụ đứng tứ giác có hai đáy là tứ giác, các mặt bên là hình chữ nhật → Hình 4.",
      "phanTichSai": {
        "A": "Đáy không phải tứ giác.",
        "B": "Đáy lục giác.",
        "C": "Đáy tam giác."
      },
      "goiYSocratic": [
        "Đáy của lăng trụ đứng tứ giác là hình gì?"
      ],
      "canhBao": "Câu hình học — node kiến thức chưa có trong graph.json (mạch Hình học đang bỏ qua)."
    },
    {
      "id": "D1-C18",
      "deNguon": "Đề 1",
      "loaiCau": "TN4",
      "mucDo": "TH",
      "mucDoSo": 2,
      "mucDoTen": "Thông hiểu",
      "diem": 0.25,
      "chuDe": "Hình lăng trụ đứng — diện tích xung quanh",
      "nodeGraph": null,
      "deBai": "Một hộp đèn dạng lăng trụ đứng tam giác có kích thước như hình. Diện tích xung quanh của hộp là:",
      "hinhAnh": "de1_c18.png",
      "phuongAn": {
        "A": "$48\\ cm^2$",
        "B": "$1200\\ cm^3$",
        "C": "$1200\\ cm^2$",
        "D": "$73\\ cm^3$"
      },
      "dapAn": "C",
      "loiGiai": "$S_{xq}=$ chu vi đáy $\\times$ chiều cao. Với số liệu trên hình, $S_{xq}=1200\\ cm^2$ (đơn vị diện tích).",
      "phanTichSai": {
        "A": "Sai số liệu.",
        "B": "Đúng số nhưng sai đơn vị ($cm^3$ là thể tích).",
        "D": "Sai cả số lẫn đơn vị."
      },
      "goiYSocratic": [
        "Công thức $S_{xq}$ của lăng trụ đứng?",
        "Diện tích dùng đơn vị gì — $cm^2$ hay $cm^3$?"
      ],
      "canhBao": "Câu hình học — node kiến thức chưa có trong graph.json (mạch Hình học đang bỏ qua)."
    },
    {
      "id": "D1-C19",
      "deNguon": "Đề 1",
      "loaiCau": "TN4",
      "mucDo": "TH",
      "mucDoSo": 2,
      "mucDoTen": "Thông hiểu",
      "diem": 0.25,
      "chuDe": "Hình hộp chữ nhật — thể tích",
      "nodeGraph": null,
      "deBai": "Một thùng carton kích thước dài $50cm$, rộng $40cm$, cao $50cm$. Thể tích của thùng là:",
      "hinhAnh": "de1_c19.png",
      "phuongAn": {
        "A": "$100\\,000\\ cm^3$",
        "B": "$10\\,000\\ cm^3$",
        "C": "$20\\,000\\ cm^3$",
        "D": "$25\\,000\\ cm^3$"
      },
      "dapAn": "A",
      "loiGiai": "$V=$ dài $\\times$ rộng $\\times$ cao $=50\\cdot40\\cdot50=100\\,000\\ cm^3$.",
      "phanTichSai": {
        "B": "Thiếu một thừa số.",
        "C": "Tính nhầm.",
        "D": "Chỉ nhân hai kích thước."
      },
      "goiYSocratic": [
        "Công thức thể tích hình hộp chữ nhật?",
        "$50\\times40\\times50=?$"
      ],
      "canhBao": "Câu hình học — node kiến thức chưa có trong graph.json (mạch Hình học đang bỏ qua)."
    },
    {
      "id": "D1-C20",
      "deNguon": "Đề 1",
      "loaiCau": "TN4",
      "mucDo": "VD",
      "mucDoSo": 3,
      "mucDoTen": "Vận dụng",
      "diem": 0.25,
      "chuDe": "Đường trung trực",
      "nodeGraph": null,
      "deBai": "Đường quốc lộ cách không xa hai điểm dân cư $A$ và $B$. Tìm địa điểm $C$ bên đường để trạm y tế cách đều $A$ và $B$. Khi đó:",
      "hinhAnh": "de1_c20.png",
      "phuongAn": {
        "A": "$C$ nằm trên đường trung trực của đoạn $AB$",
        "B": "$C$ nằm trên đường vuông góc với $AB$",
        "C": "$C$ nằm trên đường song song với $AB$",
        "D": "$C$ nằm trên đường tròn đi qua $A$ và $B$"
      },
      "dapAn": "A",
      "loiGiai": "Điểm cách đều hai đầu mút của một đoạn thẳng luôn nằm trên đường trung trực của đoạn đó.",
      "phanTichSai": {
        "B": "Vuông góc chưa đủ — phải vuông góc **tại trung điểm**.",
        "C": "Song song không đảm bảo cách đều.",
        "D": "Vô số đường tròn qua $A,B$, không xác định."
      },
      "goiYSocratic": [
        "Tập hợp các điểm cách đều hai đầu đoạn $AB$ là đường nào?"
      ],
      "canhBao": "Câu hình học — node kiến thức chưa có trong graph.json (mạch Hình học đang bỏ qua)."
    },
    {
      "id": "D1-C21",
      "deNguon": "Đề 1",
      "loaiCau": "DungSai",
      "mucDo": "VD",
      "mucDoSo": 3,
      "mucDoTen": "Vận dụng",
      "diem": 1.0,
      "chuDe": "Đại lượng tỉ lệ (nghịch)",
      "nodeGraph": "l7-dai-luong-ti-le",
      "deBai": "Ba đội máy san đất có số máy cày lần lượt $x,y,z$ (máy, $x,y,z>0$) làm ba khối lượng công việc **như nhau**. Đội 1 hoàn thành trong 8 ngày, đội 2 trong 12 ngày, đội 3 trong 16 ngày. Biết đội 1 nhiều hơn đội 3 là 6 máy.",
      "hinhAnh": null,
      "ynho": [
        {
          "ky": "a",
          "menhDe": "$\\dfrac{x}{8}=\\dfrac{y}{12}=\\dfrac{z}{16}$",
          "dapAn": "Sai",
          "giaiThich": "Số máy **tỉ lệ nghịch** với số ngày, nên $8x=12y=16z$, tức $\\dfrac{x}{\\frac18}=\\dfrac{y}{\\frac1{12}}=\\dfrac{z}{\\frac1{16}}$, KHÔNG phải $\\dfrac{x}{8}=\\dfrac{y}{12}=\\dfrac{z}{16}$ (đó là tỉ lệ thuận)."
        },
        {
          "ky": "b",
          "menhDe": "$8x=12y=16z$",
          "dapAn": "Đúng",
          "giaiThich": "Cùng một khối lượng công việc $=$ số máy $\\times$ số ngày, nên $8x=12y=16z$."
        },
        {
          "ky": "c",
          "menhDe": "$x-y=6$",
          "dapAn": "Sai",
          "giaiThich": "Đề cho đội 1 hơn đội 3 là 6 máy → $x-z=6$, không phải $x-y=6$."
        },
        {
          "ky": "d",
          "menhDe": "$x=12;\\,y=8;\\,z=6$",
          "dapAn": "Đúng",
          "giaiThich": "Kiểm tra: $8\\cdot12=12\\cdot8=16\\cdot6=96$ ✔ và $x-z=12-6=6$ ✔."
        }
      ],
      "goiYSocratic": [
        "Số máy nhiều thì thời gian ít — đây là tỉ lệ thuận hay nghịch?",
        "'Khối lượng công việc' bằng số máy nhân số ngày, viết đẳng thức đó.",
        "'Đội 1 hơn đội 3' cho hệ thức giữa hai biến nào?"
      ]
    },
    {
      "id": "D1-C22",
      "deNguon": "Đề 1",
      "loaiCau": "DungSai",
      "mucDo": "NB",
      "mucDoSo": 1,
      "mucDoTen": "Nhận biết",
      "diem": 1.0,
      "chuDe": "Đường trung trực — tam giác cân",
      "nodeGraph": null,
      "deBai": "Gọi $I$ là trung điểm đoạn $AB$, $M$ là điểm không nằm trên $AB$ sao cho $MA=MB$ (xem hình).",
      "hinhAnh": "de1_c22.png",
      "ynho": [
        {
          "ky": "a",
          "menhDe": "$\\triangle MIA=\\triangle MIB$",
          "dapAn": "Đúng",
          "giaiThich": "$MA=MB$, $IA=IB$ ($I$ trung điểm), $MI$ chung → bằng nhau (c.c.c)."
        },
        {
          "ky": "b",
          "menhDe": "$MI$ là đường trung trực của đoạn $AB$",
          "dapAn": "Đúng",
          "giaiThich": "$M$ và $I$ đều cách đều $A,B$ nên $MI$ là trung trực của $AB$."
        },
        {
          "ky": "c",
          "menhDe": "$MI\\perp AB$",
          "dapAn": "Đúng",
          "giaiThich": "Trung trực vuông góc với $AB$ tại trung điểm $I$."
        },
        {
          "ky": "d",
          "menhDe": "Tam giác $MAB$ đều",
          "dapAn": "Sai",
          "giaiThich": "Chỉ suy ra $MAB$ **cân** tại $M$ ($MA=MB$); không có dữ kiện $MA=AB$ nên chưa thể đều."
        }
      ],
      "goiYSocratic": [
        "$IA$ và $IB$ có bằng nhau không? Vì sao?",
        "Điểm cách đều hai đầu $AB$ nằm trên đường gì?",
        "'Cân' và 'đều' khác nhau ở điểm nào?"
      ],
      "canhBao": "Câu hình học — node kiến thức chưa có trong graph.json (mạch Hình học đang bỏ qua)."
    },
    {
      "id": "D1-B1",
      "deNguon": "Đề 1",
      "loaiCau": "TuLuan",
      "mucDo": "TH",
      "mucDoSo": 2,
      "mucDoTen": "Thông hiểu",
      "diem": 1.0,
      "chuDe": "Đa thức một biến",
      "nodeGraph": "l7-da-thuc-mot-bien",
      "deBai": "Cho các đa thức $P(x)=4x^3-7x^2+3x-12$; $Q(x)=-4x^3+5x^2-9x+12$ và $G(x)=x$. a) Tính $P(x)+Q(x)$. b) Tính $P(x)\\cdot G(x)$.",
      "hinhAnh": null,
      "phuongAn": null,
      "dapAn": null,
      "loiGiai": "a) $P+Q=(4x^3-4x^3)+(-7x^2+5x^2)+(3x-9x)+(-12+12)=-2x^2-6x$. b) $P\\cdot G=x(4x^3-7x^2+3x-12)=4x^4-7x^3+3x^2-12x$.",
      "phanTichSai": {},
      "goiYSocratic": [
        "Cộng đa thức: cộng các hạng tử **đồng dạng**.",
        "Nhân đơn thức $x$ với từng hạng tử của $P(x)$."
      ]
    },
    {
      "id": "D1-B2",
      "deNguon": "Đề 1",
      "loaiCau": "TuLuan",
      "mucDo": "VD",
      "mucDoSo": 3,
      "mucDoTen": "Vận dụng",
      "diem": 1.0,
      "chuDe": "Tam giác bằng nhau — quan hệ cạnh góc",
      "nodeGraph": null,
      "deBai": "Cho $\\triangle ABC$ vuông tại $A$ có $AB<AC$, kẻ phân giác $BD$ của $\\widehat{ABC}$ ($D\\in AC$). Kẻ $DM\\perp BC$ tại $M$. a) (TH) Chứng minh $\\triangle DAB=\\triangle DMB$. b) (VD) Chứng minh $AD<DC$.",
      "hinhAnh": null,
      "phuongAn": null,
      "dapAn": null,
      "loiGiai": "a) Xét $\\triangle DAB$ và $\\triangle DMB$: $\\hat A=\\hat M=90^\\circ$; $\\widehat{ABD}=\\widehat{MBD}$ (BD phân giác); $BD$ chung → $\\triangle DAB=\\triangle DMB$ (cạnh huyền–góc nhọn). b) Từ (a) suy ra $AD=MD$. Trong $\\triangle DMC$ vuông tại $M$ có $DC$ là cạnh huyền nên $DC>MD=AD$. Vậy $AD<DC$.",
      "phanTichSai": {},
      "goiYSocratic": [
        "Hai tam giác vuông chung cạnh huyền $BD$, thêm yếu tố gì bằng nhau?",
        "$AD$ bằng đoạn nào? Trong tam giác vuông, cạnh huyền so với cạnh góc vuông thế nào?"
      ],
      "canhBao": "Câu hình học — node kiến thức chưa có trong graph.json (mạch Hình học đang bỏ qua)."
    },
    {
      "id": "D1-B3",
      "deNguon": "Đề 1",
      "loaiCau": "TuLuan",
      "mucDo": "VDC",
      "mucDoSo": 4,
      "mucDoTen": "Vận dụng cao",
      "diem": 1.0,
      "chuDe": "Bất đẳng thức tam giác — thực tiễn",
      "nodeGraph": null,
      "deBai": "Ba thành phố $A,B,C$ là ba đỉnh của một tam giác, $AB=30$ km, $AC=65$ km. a) Đặt ở $B$ máy phát sóng bán kính 34 km thì trong $A,C$ thành phố nào nhận được tín hiệu? Vì sao? b) Câu hỏi tương tự với bán kính 110 km.",
      "hinhAnh": null,
      "phuongAn": null,
      "dapAn": null,
      "loiGiai": "Theo bất đẳng thức tam giác: $AC-AB<BC<AC+AB \\Rightarrow 35<BC<95$. a) Bán kính 34 km: $A$ nhận được (vì $BA=30<34$); $C$ không nhận (vì $BC>35>34$). b) Bán kính 110 km: cả $A$ và $C$ đều nhận (vì $BA=30<110$ và $BC<95<110$).",
      "phanTichSai": {},
      "goiYSocratic": [
        "Chặn $BC$ bằng bất đẳng thức tam giác từ $AB, AC$.",
        "So sánh bán kính phát sóng với khoảng cách $BA$ và khoảng $BC$."
      ],
      "canhBao": "Câu hình học — node kiến thức chưa có trong graph.json (mạch Hình học đang bỏ qua)."
    }
  ]
}